ezarr/__init__.py
ezarr/_repr.py
ezarr/common.py
ezarr/dict.py
ezarr/errors.py
ezarr/inplace.py
ezarr/io.py
ezarr/list.py
ezarr/names.py
ezarr/object.py
ezarr/patch.py
ezarr/py.typed
ezarr/types.py
ezarr/vector.py
ezarr/view.py
ezarr/dataframe/__init__.py
ezarr/dataframe/dataframe.py
ezarr/dataframe/manager.py
ezarr/dataframe/patch.py
ezarr/indexing/__init__.py
ezarr/indexing/_typing.py
ezarr/indexing/base.py
ezarr/indexing/list.py
ezarr/indexing/optimization.py
ezarr/indexing/selection.py
ezarr/indexing/single.py
ezarr/indexing/slice.py
ezarr/indexing/special.py
ezarr/indexing/utils.py
ezarr-1.2.1.dist-info/METADATA
ezarr-1.2.1.dist-info/WHEEL
ezarr-1.2.1.dist-info/entry_points.txt
ezarr-1.2.1.dist-info/RECORD
