Metadata-Version: 2.4
Name: ezarr
Version: 1.2.1
Summary: Tools for easily working with Zarr groups and arrays
Author-email: Matteo Bouvier <matteo.bouvier@lyon.unicancer.fr>
Requires-Python: >=3.12
Requires-Dist: zarr>=3.1.3
Provides-Extra: dataframe
Requires-Dist: pandas>=2.3.3; extra == 'dataframe'
